{
  "customerId": "123456",
  "id": "00000013",
  "transactionDate": "2022-12-31",
  "type": "Swap",
  "subtype": "openInterestRateSwap",
  "reversalIndicator": false,
  "movementList": [
    {
      "type": "security",
      "movementDate": "2022-12-31",
      "financialInstrument": {
        "type": "interestSwap",
        "name": "Payer interest rate swap",
        "identificationList": [
          {
            "identifier": "swapContract1",
            "type": "otherProprietaryIdentification"
          }
        ],
        "principalAmount": 100000,
        "currencyOfDenomination": "CHF",
        "expiryDate": "2023-06-27",
        "interestRateReceived": {
          "interestRateType": "fixedInterestRate",
          "rate": 1.75,
          "dayCountBasis": "act_360",
          "paymentDate": "2023-06-27",
          "paymentFrequency": "atMaturity"
        },
        "interestRatePaid": {
          "interestRateType": "floatingInterestRate",
          "spread": 0.2,
          "basis": "LIBOR",
          "dayCountBasis": "act_360",
          "paymentDate": "2023-06-27",
          "paymentFrequency": "atMaturity"
        }
      },
      "account": {
        "id": "123456-1",
        "type": "safekeepingAccount"
      },
      "quantity": {
        "value": 1,
        "quantityType": "unit"
      },
      "positionId": "013",
      "positionCurrency": "CHF"
    }
  ],
  "postingAmounts": []
}