{
  "id": "pos-009",
  "endOfDayIndicator": true,
  "positionDate": "2023-01-04",
  "financialInstrument": {
    "type": "fxSwap",
    "name": "FX Swap, 200'000 USD to CHF",
    "identificationList": [
      {
        "identifier": "fxSwapRef112",
        "type": "otherProprietaryIdentification"
      }
    ],
    "nearAmountPaid": {
      "amount": 165000,
      "currency": "CHF"
    },
    "nearAmountReceived": {
      "amount": 200000,
      "currency": "USD"
    },
    "farAmountPaid": {
      "amount": 200000,
      "currency": "USD"
    },
    "farAmountReceived": {
      "amount": 170000,
      "currency": "CHF"
    },
    "nearMaturityDate": "2023-01-04",
    "maturityDate": "2023-06-27"
  },
  "account": {
    "id": "safekeeping-account-1",
    "type": "safekeepingAccount",
    "referenceCurrency": "CHF"
  },
  "quantity": {
    "type": "unit",
    "value": 1
  },
  "foreignExchangeRate": {
    "value": 0.9,
    "sourceCurrency": "USD",
    "targetCurrency": "CHF",
    "rateDate": "2023-01-04"
  },
  "valuation": {
    "valueInPositionCurrency": {
      "amount": 10000,
      "currency": "CHF"
    },
    "valueInReferenceCurrency": {
      "amount": 10000,
      "currency": "CHF"
    }
  },
  "name": "FX Swap, 200'000 USD to CHF",
  "currency": "USD",
  "safekeepingPlace": "INSECHZZXXX"
}